awesome_align/__init__.py
awesome_align/activations.py
awesome_align/configuration_bert.py
awesome_align/configuration_utils.py
awesome_align/file_utils.py
awesome_align/modeling.py
awesome_align/modeling_utils.py
awesome_align/run_align.py
awesome_align/run_train.py
awesome_align/sparsemax.py
awesome_align/tokenization_bert.py
awesome_align/tokenization_utils.py
awesome_align/train_utils.py
awesome_align-0.1.7.dist-info/LICENSE
awesome_align-0.1.7.dist-info/METADATA
awesome_align-0.1.7.dist-info/WHEEL
awesome_align-0.1.7.dist-info/entry_points.txt
awesome_align-0.1.7.dist-info/top_level.txt
awesome_align-0.1.7.dist-info/RECORD
